hirmeos_access_logs_local_driver/__init__.py
hirmeos_access_logs_local_driver/geolookup.py
hirmeos_access_logs_local_driver/logdata.py
hirmeos_access_logs_local_driver/process_download_logs.py
hirmeos_access_logs_local_driver-0.0.3.dist-info/LICENSE
hirmeos_access_logs_local_driver-0.0.3.dist-info/METADATA
hirmeos_access_logs_local_driver-0.0.3.dist-info/WHEEL
hirmeos_access_logs_local_driver-0.0.3.dist-info/top_level.txt
hirmeos_access_logs_local_driver-0.0.3.dist-info/RECORD
