Metadata-Version: 2.1
Name: hirmeos-access-logs-local-driver
Version: 0.0.3
Summary: Functions required by the access-logs-local-driver
Author-email: Cristian Garcia <cristian.garcia@ubiquitypress.com>
Project-URL: Homepage, https://github.com/hirmeos/access_logs_driver
Classifier: Programming Language :: Python :: 3
Classifier: License :: OSI Approved :: MIT License
Classifier: Operating System :: OS Independent
Requires-Python: >=3.10
License-File: LICENSE
Requires-Dist: hirmeos-clients (>=0.1.6)
